misty-0.0.13.data/scripts/ReadPropertyMultiple
misty-0.0.13.data/scripts/ReadPropertyMultipleServer
misty-0.0.13.data/scripts/bc
misty-0.0.13.data/scripts/WhoIsIAm
misty-0.0.13.data/scripts/cp_ini
misty-0.0.13.data/scripts/ReadWriteProperty
misty-0.0.13.data/scripts/bs
misty-0.0.13.data/scripts/ReadProperty
misty-0.0.13.data/scripts/CommandableMixin
misty/__init__.py
misty/mstplib/libmstp_agent_darwin.so
misty/mstplib/libmstp_agent_linux.so
misty/mstplib/__init__.py
misty-0.0.13.dist-info/WHEEL
misty-0.0.13.dist-info/METADATA
misty-0.0.13.dist-info/top_level.txt
misty-0.0.13.dist-info/RECORD
misty-0.0.13.dist-info/LICENSE
