Metadata-Version: 1.2
Name: misty
Version: 0.0.13
Summary: MSTP support for bacpypes
Home-page: https://github.com/riptideio/misty
Author: Riptide, Inc
Author-email: raghavan@riptideio.com
Maintainer: Riptide, Inc
Maintainer-email: raghavan@riptideio.com
License: GNU General Public License v2.0
Platform: UNKNOWN
